PyQt6/Qt/lib/libQt63DAnimation.so.6
PyQt6/Qt/lib/libQt63DCore.so.6
PyQt6/Qt/lib/libQt63DExtras.so.6
PyQt6/Qt/lib/libQt63DInput.so.6
PyQt6/Qt/lib/libQt63DLogic.so.6
PyQt6/Qt/lib/libQt63DQuickAnimation.so.6
PyQt6/Qt/lib/libQt63DQuickExtras.so.6
PyQt6/Qt/lib/libQt63DQuickInput.so.6
PyQt6/Qt/lib/libQt63DQuickRender.so.6
PyQt6/Qt/lib/libQt63DQuickScene2D.so.6
PyQt6/Qt/lib/libQt63DRender.so.6
PyQt6/Qt/lib/libQt6Concurrent.so.6
PyQt6/Qt/qml/Qt3D/Animation/libquick3danimationplugin.so
PyQt6/Qt/qml/Qt3D/Animation/plugins.qmltypes
PyQt6/Qt/qml/Qt3D/Animation/qmldir
PyQt6/Qt/qml/Qt3D/Core/libquick3dcoreplugin.so
PyQt6/Qt/qml/Qt3D/Core/plugins.qmltypes
PyQt6/Qt/qml/Qt3D/Core/qmldir
PyQt6/Qt/qml/Qt3D/Extras/libquick3dextrasplugin.so
PyQt6/Qt/qml/Qt3D/Extras/plugins.qmltypes
PyQt6/Qt/qml/Qt3D/Extras/qmldir
PyQt6/Qt/qml/Qt3D/Input/libquick3dinputplugin.so
PyQt6/Qt/qml/Qt3D/Input/plugins.qmltypes
PyQt6/Qt/qml/Qt3D/Input/qmldir
PyQt6/Qt/qml/Qt3D/Logic/libquick3dlogicplugin.so
PyQt6/Qt/qml/Qt3D/Logic/plugins.qmltypes
PyQt6/Qt/qml/Qt3D/Logic/qmldir
PyQt6/Qt/qml/Qt3D/Render/libquick3drenderplugin.so
PyQt6/Qt/qml/Qt3D/Render/plugins.qmltypes
PyQt6/Qt/qml/Qt3D/Render/qmldir
PyQt6_3D_Qt-6.0.1.dist-info/LICENSE
PyQt6_3D_Qt-6.0.1.dist-info/METADATA
PyQt6_3D_Qt-6.0.1.dist-info/WHEEL
PyQt6_3D_Qt-6.0.1.dist-info/RECORD
